notebooks/dataset_api.ipynb
papers/README.md
papers/2024/GPAM/README.md
papers/2024/GPAM/gpam_ecc_cm1.py
papers/2024/GPAM/train_with_config.py
papers/2024/GPAM/configurations/ECC_CM0.json
papers/2024/GPAM/configurations/ECC_CM0_result.json
papers/2024/GPAM/configurations/ECC_CM1_k0.json
papers/2024/GPAM/configurations/ECC_CM1_k0_result.json
papers/2024/GPAM/configurations/ECC_CM2_black_box.json
papers/2024/GPAM/configurations/ECC_CM2_black_box_result.json
papers/2024/GPAM/configurations/ECC_CM2_k0.json
papers/2024/GPAM/configurations/ECC_CM2_k0_result.json
papers/2024/GPAM/configurations/ECC_CM3_k0.json
papers/2024/GPAM/configurations/ECC_CM3_k0_result.json
papers/datasets/ECC/GPAM/README.md
scaaml/__init__.py
scaaml/aes.py
scaaml/aes_forward.py
scaaml/model.py
scaaml/plot.py
scaaml/utils.py
scaaml/capture/__init__.py
scaaml/capture/capture_runner.py
scaaml/capture/communication.py
scaaml/capture/control.py
scaaml/capture/crypto_alg.py
scaaml/capture/crypto_input.py
scaaml/capture/aes/__init__.py
scaaml/capture/aes/acqktp.py
scaaml/capture/aes/aes_capture.py
scaaml/capture/aes/aes_capture_contexts.py
scaaml/capture/aes/capture_runner.py
scaaml/capture/aes/communication.py
scaaml/capture/aes/control.py
scaaml/capture/aes/crypto_alg.py
scaaml/capture/aes/crypto_input.py
scaaml/capture/ascad/ascad_capture.py
scaaml/capture/input_generators/__init__.py
scaaml/capture/input_generators/attack_point_iterator.py
scaaml/capture/input_generators/attack_point_iterator_exceptions.py
scaaml/capture/input_generators/input_generators.py
scaaml/capture/scope/__init__.py
scaaml/capture/scope/cw_scope.py
scaaml/capture/scope/default_cw_scope.py
scaaml/capture/scope/picoscope.py
scaaml/capture/scope/ps6424e.py
scaaml/capture/scope/scope_base.py
scaaml/capture/scope/scope_template.py
scaaml/capture/scope/lecroy/__init__.py
scaaml/capture/scope/lecroy/lecroy.py
scaaml/capture/scope/lecroy/lecroy_communication.py
scaaml/capture/scope/lecroy/lecroy_waveform.py
scaaml-3.0.5.dist-info/licenses/LICENSE
scaaml-3.0.5.dist-info/METADATA
scaaml-3.0.5.dist-info/WHEEL
scaaml-3.0.5.dist-info/top_level.txt
scaaml-3.0.5.dist-info/RECORD
