Metadata-Version: 2.4
Name: scaaml
Version: 3.0.5
Summary: Side Channel Attack Assisted with Machine Learning
Author: Elie Bursztein, Luca Invernizzi, Karel Král, Jean-Michel Picod
License: Apache License 2.0
Project-URL: Homepage, https://github.com/google/scaaml
Project-URL: Bug Tracker, https://github.com/google/scaaml
Keywords: machine learning,dataset,side channel attack
Classifier: Development Status :: 5 - Production/Stable
Classifier: Environment :: Console
Classifier: Framework :: Jupyter
Classifier: License :: OSI Approved :: Apache Software License
Classifier: Intended Audience :: Science/Research
Classifier: Programming Language :: Python :: 3
Classifier: Topic :: Scientific/Engineering :: Artificial Intelligence
Requires-Python: >=3.10
License-File: LICENSE
Requires-Dist: Pillow
Requires-Dist: chipwhisperer
Requires-Dist: colorama
Requires-Dist: cryptography
Requires-Dist: matplotlib
Requires-Dist: networkx[default]
Requires-Dist: numpy
Requires-Dist: pandas
Requires-Dist: picosdk
Requires-Dist: pip
Requires-Dist: pygments
Requires-Dist: pyvisa
Requires-Dist: pyvisa-py
Requires-Dist: scipy
Requires-Dist: semver
Requires-Dist: setuptools
Requires-Dist: tabulate
Requires-Dist: tensorflow
Requires-Dist: termcolor
Requires-Dist: tqdm
Requires-Dist: wheel
Provides-Extra: dev
Requires-Dist: mypy; extra == "dev"
Requires-Dist: pydantic; extra == "dev"
Requires-Dist: pytest; extra == "dev"
Requires-Dist: pytest-cov; extra == "dev"
Requires-Dist: flake8; extra == "dev"
Requires-Dist: psutil; extra == "dev"
Requires-Dist: types-cryptography; extra == "dev"
Requires-Dist: types-tensorflow; extra == "dev"
Dynamic: license-file
